setup.py
mangodistributions/__init__.py
mangodistributions.egg-info/PKG-INFO
mangodistributions.egg-info/SOURCES.txt
mangodistributions.egg-info/dependency_links.txt
mangodistributions.egg-info/top_level.txt