Metadata-Version: 2.1
Name: mangodistributions
Version: 0.0.2
Summary: A distribution package
Home-page: https://github.com/pypa/sampleproject
Author: Michael Teckman
Author-email: michael.teckman@googlemail.com
License: UNKNOWN
Platform: UNKNOWN
Classifier: Programming Language :: Python :: 3
Classifier: Operating System :: OS Independent
